{
  "DevBlogs / PowerShell Team": {
    "timestamp": "2024-04-03T01:21:10.458Z"
  },
  "DevBlogs / Windows Command Line": {
    "timestamp": "2024-08-27T20:27:36.099Z"
  },
  "Habr / DevOps": {
    "timestamp": "2024-10-07T06:37:22.368Z"
  },
  "Habr / IT-инфраструктура": {
    "timestamp": "2024-10-10T10:33:14.365Z"
  },
  "Habr / Kubernetes": {
    "timestamp": "2024-09-02T22:29:29.504Z"
  },
  "Habr / PostgreSQL": {
    "timestamp": "2024-10-09T10:34:15.308Z"
  },
  "Kubernetes": {
    "timestamp": "2024-10-03T06:36:20.295Z"
  }
}
