{
  "DevBlogs / PowerShell Team": {
    "timestamp": "2023-07-17T22:26:08.108Z"
  },
  "DevBlogs / Windows Command Line": {
    "timestamp": "2023-07-11T12:48:43.407Z"
  },
  "Habr / DevOps": {
    "timestamp": "2023-07-14T14:26:56.412Z"
  },
  "Habr / IT-инфраструктура": {
    "timestamp": "2023-07-18T18:29:14.382Z"
  },
  "Habr / Kubernetes": {
    "timestamp": "2023-07-11T20:25:17.694Z"
  },
  "Habr / PostgreSQL": {
    "timestamp": "2023-07-05T06:32:35.032Z"
  },
  "Kubernetes": {
    "timestamp": "2023-07-20T01:43:51.539Z"
  }
}
